collective.collectiongathering-1.1-py3.11-nspkg.pth
collective/collectiongathering/__init__.py
collective/collectiongathering/configure.zcml
collective/collectiongathering/content.py
collective/collectiongathering/interfaces.py
collective/collectiongathering/setuphandlers.py
collective/collectiongathering/testing.py
collective/collectiongathering/browser/__init__.py
collective/collectiongathering/browser/configure.zcml
collective/collectiongathering/browser/views.py
collective/collectiongathering/browser/templates/full_view.pt
collective/collectiongathering/browser/templates/listing.pt
collective/collectiongathering/browser/templates/listing_album.pt
collective/collectiongathering/browser/templates/listing_summary.pt
collective/collectiongathering/browser/templates/listing_tabular.pt
collective/collectiongathering/locales/collective.collectiongathering.pot
collective/collectiongathering/locales/update.sh
collective/collectiongathering/profiles/default/browserlayer.xml
collective/collectiongathering/profiles/default/collectivecollectiongathering_marker.txt
collective/collectiongathering/profiles/default/metadata.xml
collective/collectiongathering/profiles/default/types.xml
collective/collectiongathering/profiles/default/types/CollectionGathering.xml
collective/collectiongathering/profiles/uninstall/browserlayer.xml
collective/collectiongathering/profiles/uninstall/types.xml
collective/collectiongathering/tests/__init__.py
collective/collectiongathering/tests/test_collectiongathering.py
collective/collectiongathering/tests/test_setup.py
collective.collectiongathering-1.1.dist-info/METADATA
collective.collectiongathering-1.1.dist-info/WHEEL
collective.collectiongathering-1.1.dist-info/entry_points.txt
collective.collectiongathering-1.1.dist-info/namespace_packages.txt
collective.collectiongathering-1.1.dist-info/top_level.txt
collective.collectiongathering-1.1.dist-info/RECORD
